slapy/__init__.py
slapy/setup.py
slapy/graph/Transitive_Closure_DFS.py
slapy/graph/__init__.py
slapy/graph/checkDiGraphStronglyConnected.py
slapy/graph/clone_graph.py
slapy/graph/cycle_detection.py
slapy/graph/dijkstra.py
slapy/graph/find_all_cliques.py
slapy/graph/find_path.py
slapy/graph/markov_chain.py
slapy/graph/minimum_spanning_tree.py
slapy/graph/pathBetweenTwoVerticesInDiGraph.py
slapy/graph/satisfiability.py
slapy/graph/tarjan.py
slapy/graph/traversal.py
slapy/graph/util.py
slapy/graph/aoe/AOE.py
slapy/graph/aoe/__init__.py
slapy/graph/dijkstra/__init__.py
slapy/graph/dijkstra/_dijkstra.py
slapy/graph/spfa/__init__.py
slapy/graph/spfa/_spfa.py
slapy/prediction/__init__.py
slapy/prediction/gm.py
slapy/prediction/util/PredictionModel.py
slapy/prediction/util/__init__.py
slapy/swarm/__init__.py
slapy/swarm/afas/AFASEngine.py
slapy/swarm/afas/AFASIndividual.py
slapy/swarm/afas/__init__.py
slapy/swarm/ba/BAEngine.py
slapy/swarm/ba/Bat.py
slapy/swarm/ba/__init__.py
slapy/swarm/bas/BASEngine.py
slapy/swarm/bas/__init__.py
slapy/swarm/bfo/BFOEngine.py
slapy/swarm/bfo/Bacterial.py
slapy/swarm/bfo/__init__.py
slapy/swarm/cs/CSEngine.py
slapy/swarm/cs/Cuckoo.py
slapy/swarm/cs/__init__.py
slapy/swarm/cso/CSOEngine.py
slapy/swarm/cso/CSOParticle.py
slapy/swarm/cso/__init__.py
slapy/swarm/fa/FAEngine.py
slapy/swarm/fa/Firefly.py
slapy/swarm/fa/__init__.py
slapy/swarm/foa/FOAEngine.py
slapy/swarm/foa/Fly.py
slapy/swarm/foa/__init__.py
slapy/swarm/fwa/FWAEngine.py
slapy/swarm/fwa/Firework.py
slapy/swarm/fwa/__init__.py
slapy/swarm/ga/__init__.py
slapy/swarm/ga/_ga.py
slapy/swarm/ga/analysis/__init__.py
slapy/swarm/ga/analysis/console_output.py
slapy/swarm/ga/analysis/fitness_store.py
slapy/swarm/ga/components/__init__.py
slapy/swarm/ga/operators/__init__.py
slapy/swarm/ga/operators/uniform_crossover.py
slapy/swarm/ga/plugin_interfaces/__init__.py
slapy/swarm/ga/plugin_interfaces/analysis.py
snowland_algorithm-0.0.7.dist-info/DESCRIPTION.rst
snowland_algorithm-0.0.7.dist-info/METADATA
snowland_algorithm-0.0.7.dist-info/RECORD
snowland_algorithm-0.0.7.dist-info/WHEEL
snowland_algorithm-0.0.7.dist-info/metadata.json
snowland_algorithm-0.0.7.dist-info/top_level.txt
