Metadata-Version: 2.0
Name: snowland-algorithm
Version: 0.0.7
Summary: Python implementation algorithm
Home-page: https://gitee.com/hoops/snowland-algorithm-python
Author: A.Star
Author-email: astar@snowland.ltd
License: BSD License
Platform: all
Classifier: Development Status :: 4 - Beta
Classifier: Operating System :: OS Independent
Classifier: Intended Audience :: Developers
Classifier: License :: OSI Approved :: BSD License
Classifier: Programming Language :: Python
Classifier: Programming Language :: Python :: Implementation
Classifier: Programming Language :: Python :: 2
Classifier: Programming Language :: Python :: 2.7
Classifier: Programming Language :: Python :: 3
Classifier: Programming Language :: Python :: 3.4
Classifier: Programming Language :: Python :: 3.5
Classifier: Programming Language :: Python :: 3.6
Classifier: Topic :: Software Development :: Libraries
Requires-Dist: numpy (>=1.12.0)
Requires-Dist: scipy (>=0.19.1)
Requires-Dist: matplotlib (>=2.1.2)
Requires-Dist: networkx (==2.1)
